cords/__init__.py
cords/test.py
cords/selectionstrategies/__init__.py
cords/selectionstrategies/SL/__init__.py
cords/selectionstrategies/SL/adapweightsstrategy.py
cords/selectionstrategies/SL/craigstrategy.py
cords/selectionstrategies/SL/dataselectionstrategy.py
cords/selectionstrategies/SL/fixedweightstrategy.py
cords/selectionstrategies/SL/glisterstrategy.py
cords/selectionstrategies/SL/gradmatchstrategy.py
cords/selectionstrategies/SL/randomstrategy.py
cords/selectionstrategies/SL/selconstrategy.py
cords/selectionstrategies/SL/submodularselectionstrategy.py
cords/selectionstrategies/SSL/__init__.py
cords/selectionstrategies/SSL/craigstrategy.py
cords/selectionstrategies/SSL/dataselectionstrategy.py
cords/selectionstrategies/SSL/gradmatchstrategy.py
cords/selectionstrategies/SSL/randomstrategy.py
cords/selectionstrategies/SSL/retrievestrategy.py
cords/selectionstrategies/helpers/__init__.py
cords/selectionstrategies/helpers/omp_solvers.py
cords/selectionstrategies/helpers/optimalWeights.py
cords/selectionstrategies/helpers/ssl_lib/__init__.py
cords/selectionstrategies/helpers/ssl_lib/algs/__init__.py
cords/selectionstrategies/helpers/ssl_lib/algs/builder.py
cords/selectionstrategies/helpers/ssl_lib/algs/consistency.py
cords/selectionstrategies/helpers/ssl_lib/algs/ict.py
cords/selectionstrategies/helpers/ssl_lib/algs/pseudo_label.py
cords/selectionstrategies/helpers/ssl_lib/algs/utils.py
cords/selectionstrategies/helpers/ssl_lib/algs/vat.py
cords/selectionstrategies/helpers/ssl_lib/consistency/__init__.py
cords/selectionstrategies/helpers/ssl_lib/consistency/builder.py
cords/selectionstrategies/helpers/ssl_lib/consistency/cross_entropy.py
cords/selectionstrategies/helpers/ssl_lib/consistency/kl_divergence.py
cords/selectionstrategies/helpers/ssl_lib/consistency/mean_squared.py
cords/selectionstrategies/helpers/ssl_lib/misc/__init__.py
cords/selectionstrategies/helpers/ssl_lib/misc/meter.py
cords/selectionstrategies/helpers/ssl_lib/param_scheduler/__init__.py
cords-0.0.4.dist-info/LICENSE.txt
cords-0.0.4.dist-info/METADATA
cords-0.0.4.dist-info/WHEEL
cords-0.0.4.dist-info/top_level.txt
cords-0.0.4.dist-info/RECORD
